INFINITE_BATTLE_RPG/infinite_battle_rpg.py
INFINITE_BATTLE_RPG-1.1.dist-info/LICENSE
INFINITE_BATTLE_RPG-1.1.dist-info/METADATA
INFINITE_BATTLE_RPG-1.1.dist-info/WHEEL
INFINITE_BATTLE_RPG-1.1.dist-info/entry_points.txt
INFINITE_BATTLE_RPG-1.1.dist-info/top_level.txt
INFINITE_BATTLE_RPG-1.1.dist-info/RECORD
